{"is_source_file": true, "format": "JavaScript (React JSX)", "description": "React component for the Add Todo screen in a to-do application. It provides a form for entering a task title and details, with back navigation and submission handling.", "external_files": ["./AddTodo.module.css"], "external_methods": ["window.history.back", "React.useState", "alert"], "published": ["AddTodo"], "classes": [], "methods": [{"name": "AddTodo()", "description": "React functional component that renders the Add Todo page with input fields and a submit button.", "scope": "", "scopeKind": ""}], "calls": ["window.history.back", "React.useState", "alert"], "search-terms": ["AddTodo React Component", "Add Todo form", "useState hooks", "Back button navigation", "Todo input fields"], "state": 2, "file_id": 13, "knowledge_revision": 26, "git_revision": "", "ctags": [{"_type": "tag", "name": "${styles[\"input-label\"]} ${styles[\"input-detail-label\"]}", "path": "/home/kavia/workspace/code-generation/simple-todo-application-10666-10675/todo_frontend/src/AddTodo.js", "pattern": "/^            className={`${styles[\"input-label\"]} ${styles[\"input-detail-label\"]}`}$/", "language": "JavaScript", "kind": "field", "scope": "AddTodo.className", "scopeKind": "class"}, {"_type": "tag", "name": "AddTodo", "path": "/home/kavia/workspace/code-generation/simple-todo-application-10666-10675/todo_frontend/src/AddTodo.js", "pattern": "/^function AddTodo() {$/", "language": "JavaScript", "kind": "function", "signature": "()"}, {"_type": "tag", "name": "detail", "path": "/home/kavia/workspace/code-generation/simple-todo-application-10666-10675/todo_frontend/src/AddTodo.js", "pattern": "/^            value={detail}$/", "language": "JavaScript", "kind": "field", "scope": "AddTodo.required", "scopeKind": "class"}, {"_type": "tag", "name": "goBack", "path": "/home/kavia/workspace/code-generation/simple-todo-application-10666-10675/todo_frontend/src/AddTodo.js", "pattern": "/^          onClick={goBack}$/", "language": "JavaScript", "kind": "field", "scope": "AddTodo.onClick", "scopeKind": "class"}, {"_type": "tag", "name": "handleSubmit", "path": "/home/kavia/workspace/code-generation/simple-todo-application-10666-10675/todo_frontend/src/AddTodo.js", "pattern": "/^          onSubmit={handleSubmit}$/", "language": "JavaScript", "kind": "field", "scope": "AddTodo.onSubmit", "scopeKind": "class"}, {"_type": "tag", "name": "styles", "path": "/home/kavia/workspace/code-generation/simple-todo-application-10666-10675/todo_frontend/src/AddTodo.js", "pattern": "/^            className={styles[\"add-todo-input\"]}$/", "language": "JavaScript", "kind": "field", "scope": "AddTodo.className", "scopeKind": "class"}, {"_type": "tag", "name": "styles", "path": "/home/kavia/workspace/code-generation/simple-todo-application-10666-10675/todo_frontend/src/AddTodo.js", "pattern": "/^          className={styles[\"add-todo-form\"]}$/", "language": "JavaScript", "kind": "field", "scope": "AddTodo.className", "scopeKind": "class"}, {"_type": "tag", "name": "styles", "path": "/home/kavia/workspace/code-generation/simple-todo-application-10666-10675/todo_frontend/src/AddTodo.js", "pattern": "/^          className={styles[\"appbar-back-btn\"]}$/", "language": "JavaScript", "kind": "field", "scope": "AddTodo.className", "scopeKind": "class"}, {"_type": "tag", "name": "styles", "path": "/home/kavia/workspace/code-generation/simple-todo-application-10666-10675/todo_frontend/src/AddTodo.js", "pattern": "/^    <div className={styles[\"add-todo-screen\"]}>$/", "language": "JavaScript", "kind": "field", "scope": "AddTodo.AnonymousClass3ec6286a0101", "scopeKind": "class"}, {"_type": "tag", "name": "title", "path": "/home/kavia/workspace/code-generation/simple-todo-application-10666-10675/todo_frontend/src/AddTodo.js", "pattern": "/^            value={title}$/", "language": "JavaScript", "kind": "field", "scope": "AddTodo.required", "scopeKind": "class"}], "hash": "67519c24eed0a7eaef3b80772408678d", "format-version": 4, "code-base-name": "todo_frontend", "filename": "todo_frontend/src/AddTodo.js", "fields": [{"name": "className={`${styles[\"input-label\"]} ${styles[\"input-detail-label\"]}`}", "scope": "AddTodo.className", "scopeKind": "class", "description": "unavailable"}, {"name": "value={detail}", "scope": "AddTodo.required", "scopeKind": "class", "description": "unavailable"}, {"name": "onClick={goBack}", "scope": "AddTodo.onClick", "scopeKind": "class", "description": "unavailable"}, {"name": "onSubmit={handleSubmit}", "scope": "AddTodo.onSubmit", "scopeKind": "class", "description": "unavailable"}, {"name": "className={styles[\"add-todo-input\"]}", "scope": "AddTodo.className", "scopeKind": "class", "description": "unavailable"}, {"name": "className={styles[\"add-todo-form\"]}", "scope": "AddTodo.className", "scopeKind": "class", "description": "unavailable"}, {"name": "className={styles[\"appbar-back-btn\"]}", "scope": "AddTodo.className", "scopeKind": "class", "description": "unavailable"}, {"name": "<div className={styles[\"add-todo-screen\"]}>", "scope": "AddTodo.AnonymousClass3ec6286a0101", "scopeKind": "class", "description": "unavailable"}, {"name": "value={title}", "scope": "AddTodo.required", "scopeKind": "class", "description": "unavailable"}], "revision_history": [{"26": ""}]}